weightgain/Adapter.py
weightgain/Dataset.py
weightgain/Model.py
weightgain/__init__.py
weightgain/utilities.py
weightgain-1.0.0.dist-info/LICENSE
weightgain-1.0.0.dist-info/METADATA
weightgain-1.0.0.dist-info/WHEEL
weightgain-1.0.0.dist-info/top_level.txt
weightgain-1.0.0.dist-info/RECORD
