Metadata-Version: 2.2
Name: weightgain
Version: 1.0.0
Summary: Train an adapter for any embedding model in <1min
Requires-Python: >=3.12
License-File: LICENSE
Requires-Dist: json-repair>=0.39.1
Requires-Dist: litellm>=1.61.20
Requires-Dist: numpy>=2.2.3
Requires-Dist: pandas>=2.2.3
Requires-Dist: plotly>=6.0.0
Requires-Dist: scikit-learn>=1.6.1
Requires-Dist: torch>=2.6.0
Requires-Dist: tqdm>=4.67.1
